{
  "main": {
    "id": "b9edbb702ee3df62",
    "type": "split",
    "children": [
      {
        "id": "dee258e7417bcde0",
        "type": "tabs",
        "children": [
          {
            "id": "d8ba35db63ebfcbc",
            "type": "leaf",
            "state": {
              "type": "markdown",
              "state": {
                "file": "07_Communications/AI-Powered Systems Engineering.md",
                "mode": "source",
                "source": false
              },
              "icon": "lucide-file",
              "title": "AI-Powered Systems Engineering"
            }
          },
          {
            "id": "efec5b2e7ad8e457",
            "type": "leaf",
            "state": {
              "type": "tasknotes-task-list-view",
              "state": {},
              "icon": "lucide-ghost",
              "title": "tasknotes-task-list-view"
            }
          },
          {
            "id": "413db80f854c9796",
            "type": "leaf",
            "state": {
              "type": "tasknotes-advanced-calendar-view",
              "state": {},
              "icon": "calendar-range",
              "title": "Advanced Calendar"
            }
          },
          {
            "id": "51871a14242a1fb6",
            "type": "leaf",
            "state": {
              "type": "markdown",
              "state": {
                "file": "03_Meetings/EMEA Monthly 20260428.md",
                "mode": "source",
                "source": false
              },
              "icon": "lucide-file",
              "title": "EMEA Monthly 20260428"
            }
          },
          {
            "id": "0683db1cfcb022c3",
            "type": "leaf",
            "state": {
              "type": "image",
              "state": {
                "file": "Screenshot 2026-04-28 at 17.51.49.png"
              },
              "icon": "lucide-image",
              "title": "Screenshot 2026-04-28 at 17.51.49"
            }
          },
          {
            "id": "a3764d05f566f368",
            "type": "leaf",
            "state": {
              "type": "markdown",
              "state": {
                "file": "03_Meetings/03.01_Board-Meetings/Meeting Agenda and MoMs 20260517.md",
                "mode": "source",
                "source": false
              },
              "icon": "lucide-file",
              "title": "Meeting Agenda and MoMs 20260517"
            }
          },
          {
            "id": "91ec1ba77b302d8a",
            "type": "leaf",
            "state": {
              "type": "image",
              "state": {
                "file": "Pasted image 20260510185522.png"
              },
              "icon": "lucide-image",
              "title": "Pasted image 20260510185522"
            }
          },
          {
            "id": "87ce0ffd7c3e8f54",
            "type": "leaf",
            "state": {
              "type": "markdown",
              "state": {
                "file": "01_Governance/MENACOSE_People/Moataz Hassan.md",
                "mode": "source",
                "source": false
              },
              "icon": "lucide-file",
              "title": "Moataz Hassan"
            }
          },
          {
            "id": "37e0cb75a580063a",
            "type": "leaf",
            "state": {
              "type": "markdown",
              "state": {
                "file": "01_Governance/MENACOSE_People/Omar Hussein.md",
                "mode": "source",
                "source": false
              },
              "icon": "lucide-file",
              "title": "Omar Hussein"
            }
          }
        ],
        "currentTab": 5
      }
    ],
    "direction": "vertical"
  },
  "left": {
    "id": "bead697d99a00606",
    "type": "split",
    "children": [
      {
        "id": "3d7060e62a3debc4",
        "type": "tabs",
        "children": [
          {
            "id": "ad6aab63b8435264",
            "type": "leaf",
            "state": {
              "type": "file-explorer",
              "state": {
                "sortOrder": "alphabetical",
                "autoReveal": false
              },
              "icon": "lucide-folder-closed",
              "title": "Files"
            }
          },
          {
            "id": "e8ee71bd2127864d",
            "type": "leaf",
            "state": {
              "type": "search",
              "state": {
                "query": "tag:#MoatazHassan",
                "matchingCase": false,
                "explainSearch": false,
                "collapseAll": false,
                "extraContext": false,
                "sortOrder": "alphabetical"
              },
              "icon": "lucide-search",
              "title": "Search"
            }
          },
          {
            "id": "17a92458db085b84",
            "type": "leaf",
            "state": {
              "type": "bookmarks",
              "state": {},
              "icon": "lucide-bookmark",
              "title": "Bookmarks"
            }
          }
        ]
      }
    ],
    "direction": "horizontal",
    "width": 300
  },
  "right": {
    "id": "3ca7e61c889a0d46",
    "type": "split",
    "children": [
      {
        "id": "76262b4255ba5a6f",
        "type": "tabs",
        "children": [
          {
            "id": "41386d717cc1ded6",
            "type": "leaf",
            "state": {
              "type": "backlink",
              "state": {
                "file": "03_Meetings/03.01_Board-Meetings/Meeting Agenda and MoMs 20260517.md",
                "collapseAll": false,
                "extraContext": false,
                "sortOrder": "alphabetical",
                "showSearch": false,
                "searchQuery": "",
                "backlinkCollapsed": false,
                "unlinkedCollapsed": true
              },
              "icon": "links-coming-in",
              "title": "Backlinks for Meeting Agenda and MoMs 20260517"
            }
          },
          {
            "id": "d48572fd1bba463d",
            "type": "leaf",
            "state": {
              "type": "outgoing-link",
              "state": {
                "file": "Publish Obsidian Vault.md",
                "linksCollapsed": false,
                "unlinkedCollapsed": true
              },
              "icon": "links-going-out",
              "title": "Outgoing links from Publish Obsidian Vault"
            }
          },
          {
            "id": "ebafc71b78d1a12d",
            "type": "leaf",
            "state": {
              "type": "tag",
              "state": {
                "sortOrder": "frequency",
                "useHierarchy": true,
                "showSearch": false,
                "searchQuery": ""
              },
              "icon": "lucide-tags",
              "title": "Tags"
            }
          },
          {
            "id": "0ea708f647d15adf",
            "type": "leaf",
            "state": {
              "type": "outline",
              "state": {
                "file": "90_Attachments/Untitled.md",
                "followCursor": false,
                "showSearch": false,
                "searchQuery": ""
              },
              "icon": "lucide-list",
              "title": "Outline of Untitled"
            }
          },
          {
            "id": "37e6e558e7b6ce0a",
            "type": "leaf",
            "state": {
              "type": "footnotes",
              "state": {
                "file": "90_Attachments/Untitled.md"
              },
              "icon": "lucide-file-signature",
              "title": "Footnotes"
            }
          },
          {
            "id": "ad45b4f117120172",
            "type": "leaf",
            "state": {
              "type": "all-properties",
              "state": {
                "sortOrder": "frequency",
                "showSearch": false,
                "searchQuery": ""
              },
              "icon": "lucide-archive",
              "title": "All properties"
            }
          }
        ]
      }
    ],
    "direction": "horizontal",
    "width": 393.5
  },
  "left-ribbon": {
    "hiddenItems": {
      "switcher:Open quick switcher": false,
      "graph:Open graph view": false,
      "canvas:Create new canvas": false,
      "templates:Insert template": false,
      "command-palette:Open command palette": false,
      "bases:Create new base": false,
      "workspaces:Manage workspace layouts": false,
      "obsidian-excalidraw-plugin:New drawing": false,
      "tasknotes:Open mini calendar": false,
      "tasknotes:Open advanced calendar": false,
      "tasknotes:Open task list": false,
      "tasknotes:Open notes": false,
      "tasknotes:Open agenda": false,
      "tasknotes:Open kanban board": false,
      "tasknotes:Open pomodoro": false,
      "tasknotes:Open pomodoro stats": false,
      "tasknotes:Create new task": false,
      "templater-obsidian:Templater": false
    }
  },
  "floating": {
    "id": "7584d2138329c73b",
    "type": "floating",
    "children": [
      {
        "id": "0501ed1a2dc51812",
        "type": "window",
        "children": [
          {
            "id": "c26767f55ddce4da",
            "type": "tabs",
            "children": [
              {
                "id": "d18f1858e1da79c4",
                "type": "leaf",
                "state": {
                  "type": "markdown",
                  "state": {
                    "file": "03_Meetings/03.01_Board-Meetings/Meeting Agenda and MoMs 20260503.md",
                    "mode": "source",
                    "source": false
                  },
                  "icon": "lucide-file",
                  "title": "Meeting Agenda and MoMs 20260503"
                }
              }
            ]
          }
        ],
        "direction": "vertical",
        "x": 2825,
        "y": 52,
        "width": 1015,
        "height": 851,
        "maximize": true,
        "zoom": 0.5
      },
      {
        "id": "a453ed38cc2f42ce",
        "type": "window",
        "children": [
          {
            "id": "9d3647634beeff94",
            "type": "tabs",
            "children": [
              {
                "id": "d4463fdf7ebeea26",
                "type": "leaf",
                "state": {
                  "type": "markdown",
                  "state": {
                    "file": "03_Meetings/03.01_Board-Meetings/Meeting Agenda and MoMs 20260510.md",
                    "mode": "source",
                    "source": false
                  },
                  "icon": "lucide-file",
                  "title": "Meeting Agenda and MoMs 20260510"
                }
              }
            ]
          }
        ],
        "direction": "vertical",
        "x": 448,
        "y": 84,
        "width": 1024,
        "height": 800,
        "maximize": false,
        "zoom": 0.5
      }
    ]
  },
  "active": "a3764d05f566f368",
  "lastOpenFiles": [
    "03_Meetings/03.01_Board-Meetings/Meeting Agenda and MoMs 20250914.md",
    "03_Meetings/03.01_Board-Meetings/Meeting Agenda and MoMs 20251123.md",
    "03_Meetings/03.01_Board-Meetings/Meeting Agenda and MoMs 20260426.md",
    "03_Meetings/03.01_Board-Meetings/Meeting Agenda and MoMs 20260503.md",
    "03_Meetings/03.01_Board-Meetings/Meeting Agenda and MoMs 20260517.md",
    "03_Meetings/03.01_Board-Meetings/Meeting Agenda and MoMs 20260510.md",
    "Screenshot 2026-04-28 at 17.51.49.png",
    "03_Meetings/Bi-Weekly Qahwa Gathering.md",
    "02_Inbox/MENACOSE Banner.md",
    "Pasted image 20260510185522.png",
    "02_Inbox/Untitled.md",
    "02_Inbox/Untitled.canvas",
    "Screenshot 2026-04-28 at 17.49.44.png",
    "03_Meetings/EMEA Monthly 20260428.md",
    "01_Governance/By-Laws.md",
    "Pasted image 20260428182330.png",
    "Pasted image 20260428182321.png",
    "Pasted image 20260428180928.png",
    "Pasted image 20260428175913.png",
    "Pasted image 20260428175830.png",
    "Pasted image 20260428175308.png",
    "Screenshot 2026-04-28 at 17.49.44 3.png",
    "01_Governance/MENACOSE_People/Moataz Hassan.md",
    "01_Governance/MENACOSE_People/Omar Hussein.md",
    "09_Secretary/09.01_People",
    "99_Templates/Meeting Agenda and MoMs.md",
    "99_Templates/Add Project Brainstorming.md",
    "00_Meta/Drawing 2025-09-21 19.32.54.excalidraw.md",
    "05_Working-Groups/Untitled 1.md",
    "02_Inbox/Due Diligence on Proposing a New Systems Engineering Journal for the Middle East.md",
    "07_Communications/AI-Powered Systems Engineering.md",
    "07_Communications/Qahwa Gathering.md",
    "01_Governance/INCOSE Infrastructure.md",
    "01_Governance/Vision_Mission_Strategy.md",
    "01_Governance/Memberships Development.md",
    "00_Meta/Vault Organisation & Processes.md",
    "README.md",
    "90_Attachments/Untitled.md",
    "01_Governance/MENACOSE_People",
    "07_Communications/Query Communication.base",
    "09_Secretary",
    "TaskNotes/Tasks",
    "TaskNotes",
    "Untitled.canvas",
    "04_Projects-AND-Initiatives/04.01_Events",
    "03_Meetings/03.02_General-Meetings",
    "03_Meetings/03.01_Board-Meetings",
    "90_Attachments/90.01_Images"
  ]
}